ipss/__init__.py
ipss/helpers.py
ipss/main.py
ipss/preselection.py
ipss/processing.py
ipss/base_selectors/__init__.py
ipss/base_selectors/gb.py
ipss/base_selectors/linear.py
ipss/base_selectors/rf.py
ipss/base_selectors/ufi.py
ipss-1.1.10.dist-info/licenses/LICENSE
ipss-1.1.10.dist-info/METADATA
ipss-1.1.10.dist-info/WHEEL
ipss-1.1.10.dist-info/top_level.txt
ipss-1.1.10.dist-info/RECORD
