Metadata-Version: 2.4
Name: ipss
Version: 1.1.10
Summary: Python implementation of integrated path stability selection (IPSS)
Author-email: Omar Melikechi <omar.melikechi@gmail.com>
License-Expression: MIT
Project-URL: Homepage, https://github.com/omelikechi/ipss
Keywords: feature selection,variable selection,stability selection,machine learning,statistics
Classifier: Programming Language :: Python :: 3
Classifier: Operating System :: OS Independent
Requires-Python: >=3.6
License-File: LICENSE
Requires-Dist: joblib
Requires-Dist: numpy
Requires-Dist: scikit-learn
Requires-Dist: xgboost
Dynamic: license-file
